{"Annotations":[],"DocumentName":"24279 - Anklage gegen Hubschrauberpiloten von Sölden erhoben (2006-03-27)","Sentences":[{"SentenceId":0,"Tokens":["Gegen","den","Hubschrauberpiloten",",","der","am","5.","September","2005","ein","Betonteil","über","der","Gondelbahn","in","Sölden","verloren","hatte",",","hat","die","Staatsanwaltschaft","Innsbruck","Mitte","März","2006","Anklage","erhoben","."]},{"SentenceId":1,"Tokens":["Dem","Mann","wird","von","der","Staatsanwaltschaft","Innsbruck","fahrlässige","Tötung","vorgeworfen",",","da","bei","dem","Vorfall","neun","Skifahrer","aus","Bayern","und","Baden-Württemberg","starben","."]},{"SentenceId":2,"Tokens":["Den","35-jährige","Piloten","erwartet","eine","Anklage","wegen","fahrlässiger","Körperverletzung","und","fahrlässiger","Gemeingefährdung","."]},{"SentenceId":3,"Tokens":["Der","Staatsanwalt","beruft","sich","dabei","auf","amtliche","Verordnungen",",","die","bei","einem","Hubschrauberflug","mit","Lasten","über","eine","Seilbahn","hinweg","beachtet","werden","müssen","."]},{"SentenceId":4,"Tokens":["Die","Ansichten","des","Piloten",",","der","Huberschrauberfirma","sowie","des","Staatsanwaltes","weichen","in","der","Auslegung","der","Verordnung","voneinander","ab","."]},{"SentenceId":5,"Tokens":["Die","beteiligten","Parteien","legen","die","Verordnung","unterschiedlich","aus","."]},{"SentenceId":6,"Tokens":["Das","technische","Gutachten",",","auf","das","die","Staatsanwaltschaft","gewartet","hatte",",","liegt","mittlerweile","vor","."]},{"SentenceId":7,"Tokens":["Entscheiden","muss","nun","das","Gericht","."]},{"SentenceId":8,"Tokens":["Ein","genauer","Termin","für","den","Prozess","liegt","noch","nicht","fest","."]}]}