{"Annotations":[{"Addr":[],"Cue":[],"Form":"IndirectFreeIndirect","Frame":[],"HasNested":false,"IsNested":false,"Message":["12:0","12:1","12:2","12:3","12:4","12:5","12:6","12:7","12:8","12:9","12:10"],"STWR":"Speech","Source":["11:2"]}],"DocumentName":"55066 - Neues chinesisches Hybridauto auf dem Markt (2009-01-05)","Sentences":[{"SentenceId":0,"Tokens":["In","zwölf","großen","Städten","Chinas","begann","Mitte","Dezember","2008","die","Serienproduktion","und","die","Vermarktung","eines","Hybridautos","eines","landeseigenen","Unternehmens","."]},{"SentenceId":1,"Tokens":["Dabei","handelt","es","sich","um","das","Modell","„","F3","DM","“","von","der","Firma","„","Build","Your","Dreams","“",",","besser","bekannt","unter","dem","Kürzel","BYD","."]},{"SentenceId":2,"Tokens":["An","der","Firma","ist","auch","der","US-amerikanische","Investor","Warren","Buffet","zu","9,9","Prozent","beteiligt","."]},{"SentenceId":3,"Tokens":["Die","chinesische","Firma","produziert","bereits","die","Limousine","F3",",","die","im","Land","in","ihrem","Segment","Marktführer","ist","."]},{"SentenceId":4,"Tokens":["BYD",",","das","seit","2003","Autos","herstellt",",","gilt","zudem","als","Spezialist","für","elektrische","Komponenten","und","Batterien","."]},{"SentenceId":5,"Tokens":["In","reinem","Batteriebetrieb","hat","das","Fahrzeug","eine","Reichweite","von","100",",","nach","anderen","Angaben","110","Kilometern","."]},{"SentenceId":6,"Tokens":["An","einem","normalen","Stromanschluss","dauert","der","Aufladevorgang","acht",",","nach","anderen","Angaben","neun","Stunden","."]},{"SentenceId":7,"Tokens":["Das","Modell","kostet","149.800","Yuan","(","zirka","16.000","Euro",")","."]},{"SentenceId":8,"Tokens":["Der","Verkauf","in","Europa","soll","2010","starten",",","der","in","den","Vereinigten","Staaten","im","Jahr","2011."]},{"SentenceId":9,"Tokens":["Erste","Kunden","sind","die","Verwaltung","von","Shenzhen","und","die","China","Construction","Bank","."]},{"SentenceId":10,"Tokens":["Beide","Verträge","sehen","den","Verkauf","von","50","Fahrzeugen","vor","."]},{"SentenceId":11,"Tokens":["2009","will","BYD","180.000","Autos","verkaufen",",","2010","sollen","es","dann","350.000","Stück","sein","."]},{"SentenceId":12,"Tokens":["Problematisch","sei","im","Binnenmarkt","noch","die","unterentwickelte","Infrastruktur","für","Elektroautos","."]},{"SentenceId":13,"Tokens":["Kaum","ein","Wohngebäude","in","China","hat","einen","Parkplatz",",","so","dass","das","Wiederaufladen","über","Nacht","besonders","schwierig","ist","."]}]}