{"Annotations":[{"Addr":[],"Cue":["0:17"],"Form":"Indirect","Frame":["0:17","0:18","0:19"],"HasNested":false,"IsNested":false,"Message":["0:0","0:1","0:2","0:3","0:4","0:5","0:6","0:7","0:8","0:9","0:10","0:11","0:12","0:13","0:14","0:15","0:16","0:20","0:21","0:22","0:23","0:24","0:25"],"STWR":"SW","Source":["0:18","0:19"]},{"Addr":[],"Cue":[],"Form":"IndirectFreeIndirect","Frame":[],"HasNested":false,"IsNested":false,"Message":["1:8","1:9","1:10","1:11","1:12","1:13","1:14","1:15","1:16"],"STWR":"SW","Source":["0:18","0:19"]},{"Addr":[],"Cue":[],"Form":"IndirectFreeIndirect","Frame":[],"HasNested":false,"IsNested":false,"Message":["2:0","2:1","2:2","2:3","2:4","2:5","2:6","2:7","2:8","2:9","2:10","2:11","2:12","2:13","2:14","2:15","2:16","2:17","2:18","2:19","2:20","2:21","2:22","2:23","2:24","2:25","2:26","2:27","2:28","2:29","2:30","2:31","2:32","2:33","2:34"],"STWR":"SW","Source":["0:18","0:19"]},{"Addr":[],"Cue":["7:2"],"Form":"Indirect","Frame":["7:2","7:3","7:4"],"HasNested":false,"IsNested":false,"Message":["7:0","7:1","7:5","7:6","7:7","7:8","7:9","7:10","7:11","7:12"],"STWR":"SW","Source":["7:3","7:4"]}],"DocumentName":"82396 - Busunfall im Colca-Tal: zwei deutsche Touristen ums Leben gekommen (2018-04-21)","Sentences":[{"SentenceId":0,"Tokens":["Bei","einem","Busunfall","am","Freitagnachmittag","im","Colca-Tal",",","ein","sehr","beliebter","Touristenort","im","Süden","Perus",",","sind","laut","den","Angaben","zwei","deutsche","Touristen","ums","Leben","gekommen","."]},{"SentenceId":1,"Tokens":["Zwölf","andere","Mitglieder","der","Reisegruppe","wurden","verletzt",",","die","Verletzten","seien","zehn","deutsche","Touristen","und","zwei","Peruaner","."]},{"SentenceId":2,"Tokens":["Der","Kleinbus","sei","auf","dem","Weg","von","Arequipa","nach","Chivay","(","ein","Städtchen","das","etwa","3600","Meter","über","dem","Meeresspiegel","gelegen","ist",")","vom","Weg","abgeraten","und","in","einen","20","Meter","tiefen","Abgrund","hinabgestürzt","."]},{"SentenceId":3,"Tokens":["Die","Verletzten","wurden","zum","Krankenhaus","in","Arequipa","gebracht","."]},{"SentenceId":4,"Tokens":["Sehr","bemerkenswert","ist","es",",","dass","dies","schon","der","dritte","tödliche","Busunfall","in","Peru","innerhalb","nur","sehr","kurzer","Zeit","ist","."]},{"SentenceId":5,"Tokens":["In","derselben","Gegend","(","Region","Arequipa",")","geriet","am","Donnerstagabend","ein","Bus","der","auf","dem","Weg","war","von","Chuquibamba","nach","Arequipa","in","einer","Straßenkurve","vom","Weg","ab","und","stürzte","60","Meter","nach","unten","in","einen","Fluss",",","wobei","sieben","Personen","starben","und","etwa","20","verletzt","wurden","."]},{"SentenceId":6,"Tokens":["Außerdem","stürzte","in","der","Region","La","Libertad","ein","Bus","in","eine","200","Meter","tiefe","Schlucht","."]},{"SentenceId":7,"Tokens":["Dabei","sind","nach","den","Polizeiangaben","elf","Personen","gestorben","und","etwa","40","verletzt","worden","."]}]}