{
    "Annotations": [
        {
            "Addr": [],
            "AddrText": "",
            "Cue": [
                "2:1",
                "2:7"
            ],
            "CueText": "gab bekannt",
            "Form": "Indirect",
            "Frame": [
                "2:1",
                "2:2",
                "2:3",
                "2:4",
                "2:5",
                "2:6",
                "2:7"
            ],
            "FrameText": "gab Bundesverkehrsminister Manfred Stolpe in Berlin bekannt",
            "HasNested": false,
            "IsNested": false,
            "Message": [
                "0:0",
                "0:1",
                "0:2",
                "0:3",
                "0:4",
                "0:5",
                "0:6",
                "0:7",
                "0:8",
                "0:9",
                "0:10",
                "0:11",
                "0:12",
                "0:13",
                "0:14",
                "1:0",
                "1:1",
                "1:2",
                "1:3",
                "1:4",
                "1:5",
                "1:6",
                "2:0"
            ],
            "MessageText": "Der Ausbau der A1 zwischen Hamburg und Bremen soll von privaten Investoren finanziert werden . Die Refinanzierung erfolgt über die LKW-Maut . Das",
            "STWR": "Speech",
            "Source": [
                "2:2",
                "2:3",
                "2:4"
            ],
            "SourceText": "Bundesverkehrsminister Manfred Stolpe"
        }
    ],
    "DocumentName": "3574 - A1-Ausbau wird privat finanziert (2005-02-27)",
    "Sentences": [
        {
            "SentenceId": 0,
            "Tokens": [
                "Der",
                "Ausbau",
                "der",
                "A1",
                "zwischen",
                "Hamburg",
                "und",
                "Bremen",
                "soll",
                "von",
                "privaten",
                "Investoren",
                "finanziert",
                "werden",
                "."
            ]
        },
        {
            "SentenceId": 1,
            "Tokens": [
                "Die",
                "Refinanzierung",
                "erfolgt",
                "über",
                "die",
                "LKW-Maut",
                "."
            ]
        },
        {
            "SentenceId": 2,
            "Tokens": [
                "Das",
                "gab",
                "Bundesverkehrsminister",
                "Manfred",
                "Stolpe",
                "in",
                "Berlin",
                "bekannt",
                "."
            ]
        },
        {
            "SentenceId": 3,
            "Tokens": [
                "Der",
                "Abschnitt",
                "zwischen",
                "dem",
                "Buchholzer",
                "Dreieck",
                "und",
                "dem",
                "Bremer",
                "Kreuz",
                "ist",
                "das",
                "erste",
                "deutsche",
                "Autobahnprojekt",
                ",",
                "das",
                "nicht",
                "mehr",
                "aus",
                "dem",
                "Bundeshaushalt",
                "finanziert",
                "werden",
                "soll",
                "."
            ]
        },
        {
            "SentenceId": 4,
            "Tokens": [
                "Welcher",
                "Investor",
                "den",
                "Zuschlag",
                "erhält",
                ",",
                "wird",
                "im",
                "kommenden",
                "Jahr",
                "entschieden",
                "."
            ]
        },
        {
            "SentenceId": 5,
            "Tokens": [
                "Das",
                "ist",
                "das",
                "erste",
                "Mal",
                ",",
                "dass",
                "das",
                "so",
                "genannte",
                "„",
                "public-private-partnership",
                "“",
                ",",
                "eine",
                "Öffentlich-Private-Partnerschaft",
                ",",
                "für",
                "den",
                "Bau",
                "einer",
                "Bundesautobahn",
                "genutzt",
                "wird",
                "."
            ]
        },
        {
            "SentenceId": 6,
            "Tokens": [
                "Bislang",
                "war",
                "so",
                "etwas",
                "nur",
                "bei",
                "Tunneln",
                "und",
                "Brücken",
                "gesetzlich",
                "möglich",
                "."
            ]
        },
        {
            "SentenceId": 7,
            "Tokens": [
                "Nur",
                "die",
                "Planungskosten",
                "muss",
                "weiterhin",
                "der",
                "Bund",
                "tragen",
                "."
            ]
        },
        {
            "SentenceId": 8,
            "Tokens": [
                "Die",
                "A1",
                "soll",
                "in",
                "diesem",
                "Abschnitt",
                "sechsspurig",
                "ausgebaut",
                "werden",
                "."
            ]
        },
        {
            "SentenceId": 9,
            "Tokens": [
                "Dieser",
                "Plan",
                ",",
                "der",
                "von",
                "der",
                "Freien",
                "und",
                "Hansestadt",
                "Hamburg",
                ",",
                "der",
                "Hansestadt",
                "Bremen",
                "und",
                "dem",
                "Land",
                "Niedersachsen",
                "bereits",
                "seit",
                "Jahren",
                "gefordert",
                "wird",
                ",",
                "war",
                "bislang",
                "an",
                "leeren",
                "öffentlichen",
                "Kassen",
                "gescheitert",
                "."
            ]
        }
    ]
}