{
    "Annotations": [
        {
            "Addr": [],
            "AddrText": "",
            "Cue": [
                "1:15"
            ],
            "CueText": "so",
            "Form": "Indirect",
            "Frame": [
                "1:14",
                "1:15",
                "1:16",
                "1:17",
                "1:18",
                "1:19"
            ],
            "FrameText": ", so ein Sprecher des CERN",
            "HasNested": true,
            "IsNested": false,
            "Message": [
                "1:0",
                "1:1",
                "1:2",
                "1:3",
                "1:4",
                "1:5",
                "1:6",
                "1:7",
                "1:8",
                "1:9",
                "1:10",
                "1:11",
                "1:12",
                "1:13"
            ],
            "MessageText": "Das Kühlsystem war wegen „ Probleme [ n ] mit der Elektrizität “ ausgefallen",
            "STWR": "Speech",
            "Source": [
                "1:16",
                "1:17",
                "1:18",
                "1:19"
            ],
            "SourceText": "ein Sprecher des CERN"
        },
        {
            "Addr": [],
            "AddrText": "",
            "Cue": [
                "1:15"
            ],
            "CueText": "so",
            "Form": "Direct",
            "Frame": [
                "1:14",
                "1:15",
                "1:16",
                "1:17",
                "1:18",
                "1:19"
            ],
            "FrameText": ", so ein Sprecher des CERN",
            "HasNested": false,
            "IsNested": true,
            "Message": [
                "1:4",
                "1:5",
                "1:6",
                "1:7",
                "1:8",
                "1:9",
                "1:10",
                "1:11",
                "1:12"
            ],
            "MessageText": "„ Probleme [ n ] mit der Elektrizität “",
            "STWR": "Speech",
            "Source": [
                "1:16",
                "1:17",
                "1:18",
                "1:19"
            ],
            "SourceText": "ein Sprecher des CERN"
        },
        {
            "Addr": [],
            "AddrText": "",
            "Cue": [],
            "CueText": "",
            "Form": "IndirectFreeIndirect",
            "Frame": [],
            "FrameText": "",
            "HasNested": false,
            "IsNested": false,
            "Message": [
                "2:0",
                "2:1",
                "2:2",
                "2:3",
                "2:4",
                "2:5",
                "2:6",
                "2:7",
                "2:8",
                "2:9",
                "2:10",
                "2:11",
                "2:12",
                "2:13",
                "2:14",
                "2:15"
            ],
            "MessageText": "Das Problem sei aber mittlerweile gelöst , und der Large Hadron Collider werde wieder hochgefahren .",
            "STWR": "Speech",
            "Source": [
                "1:16",
                "1:17",
                "1:18",
                "1:19"
            ],
            "SourceText": "ein Sprecher des CERN"
        },
        {
            "Addr": [],
            "AddrText": "",
            "Cue": [
                "6:4"
            ],
            "CueText": "nach",
            "Form": "Indirect",
            "Frame": [
                "6:4",
                "6:5",
                "6:6",
                "6:7"
            ],
            "FrameText": "nach Berichten britischer Tageszeitungen",
            "HasNested": false,
            "IsNested": false,
            "Message": [
                "6:0",
                "6:1",
                "6:2",
                "6:3",
                "6:8",
                "6:9",
                "6:10",
                "6:11",
                "6:12",
                "6:13",
                "6:14",
                "6:15",
                "6:16",
                "6:17",
                "6:18",
                "6:19",
                "6:20",
                "6:21",
                "6:22",
                "6:23"
            ],
            "MessageText": "Vor wenigen Tagen soll außerdem ein an die Öffentlichkeit angeschlossenes Computernetzwerk für eines der Experimente des LHC gehackt worden sein",
            "STWR": "Writing",
            "Source": [
                "6:5",
                "6:6",
                "6:7"
            ],
            "SourceText": "Berichten britischer Tageszeitungen"
        },
        {
            "Addr": [
                "8:10",
                "8:11",
                "8:12",
                "8:13"
            ],
            "AddrText": "die Sicherheitstechniker am CERN",
            "Cue": [
                "8:14",
                "8:21"
            ],
            "CueText": "als bezeichnete",
            "Form": "Direct",
            "Frame": [
                "8:0",
                "8:1",
                "8:2",
                "8:3",
                "8:4",
                "8:5",
                "8:6",
                "8:7",
                "8:8",
                "8:9",
                "8:10",
                "8:11",
                "8:12",
                "8:13",
                "8:14",
                "8:21"
            ],
            "FrameText": "die Hacker hinterließen dort angeblich eine griechische Botschaft , welche die Sicherheitstechniker am CERN als bezeichnete",
            "HasNested": false,
            "IsNested": false,
            "Message": [
                "8:15",
                "8:16",
                "8:17",
                "8:18",
                "8:19",
                "8:20"
            ],
            "MessageText": "„ einen Haufen von Schulkindern “",
            "STWR": "Writing",
            "Source": [
                "8:5",
                "8:6",
                "8:7"
            ],
            "SourceText": "eine griechische Botschaft"
        }
    ],
    "DocumentName": "52987 - Pannen beim CERN: LHC nach Stromausfall abgeschaltet (2008-09-19)",
    "Sentences": [
        {
            "SentenceId": 0,
            "Tokens": [
                "Der",
                "neue",
                "Teilchenbeschleuniger",
                "Large",
                "Hadron",
                "Collider",
                "(",
                "LHC",
                ")",
                "des",
                "CERN",
                "musste",
                "am",
                "gestrigen",
                "Donnerstag",
                "nach",
                "Problemen",
                "mit",
                "dem",
                "Kühlsystem",
                "abgeschaltet",
                "werden",
                "."
            ]
        },
        {
            "SentenceId": 1,
            "Tokens": [
                "Das",
                "Kühlsystem",
                "war",
                "wegen",
                "„",
                "Probleme",
                "[",
                "n",
                "]",
                "mit",
                "der",
                "Elektrizität",
                "“",
                "ausgefallen",
                ",",
                "so",
                "ein",
                "Sprecher",
                "des",
                "CERN",
                "."
            ]
        },
        {
            "SentenceId": 2,
            "Tokens": [
                "Das",
                "Problem",
                "sei",
                "aber",
                "mittlerweile",
                "gelöst",
                ",",
                "und",
                "der",
                "Large",
                "Hadron",
                "Collider",
                "werde",
                "wieder",
                "hochgefahren",
                "."
            ]
        },
        {
            "SentenceId": 3,
            "Tokens": [
                "Der",
                "Teilchenbeschleuniger",
                "wurde",
                "gebaut",
                ",",
                "um",
                "Protonen",
                "oder",
                "andere",
                "Bestandteile",
                "von",
                "Atomkernen",
                "auf",
                "eine",
                "Geschwindigkeit",
                "nahe",
                "der",
                "Lichtgeschwindigkeit",
                "zu",
                "beschleunigen",
                "und",
                "dann",
                "aufeinander",
                "prallen",
                "zu",
                "lassen",
                "."
            ]
        },
        {
            "SentenceId": 4,
            "Tokens": [
                "Dazu",
                "ist",
                "eine",
                "Kühlung",
                "der",
                "Anlage",
                "auf",
                "Temperaturen",
                "erforderlich",
                ",",
                "die",
                "in",
                "der",
                "Nähe",
                "des",
                "absoluten",
                "Nullpunktes",
                "(",
                "minus",
                "273,15",
                "Grad",
                "Celsius",
                ")",
                "liegen",
                "."
            ]
        },
        {
            "SentenceId": 5,
            "Tokens": [
                "Zur",
                "Gewährleistung",
                "der",
                "Funktion",
                "des",
                "Teilchenbeschleunigers",
                "wird",
                "die",
                "Anlage",
                "auf",
                "eine",
                "Temperatur",
                "von",
                "minus",
                "271,3",
                "Grad",
                "Celsius",
                "(",
                "1,85",
                "Kelvin",
                ")",
                "gekühlt",
                "."
            ]
        },
        {
            "SentenceId": 6,
            "Tokens": [
                "Vor",
                "wenigen",
                "Tagen",
                "soll",
                "nach",
                "Berichten",
                "britischer",
                "Tageszeitungen",
                "außerdem",
                "ein",
                "an",
                "die",
                "Öffentlichkeit",
                "angeschlossenes",
                "Computernetzwerk",
                "für",
                "eines",
                "der",
                "Experimente",
                "des",
                "LHC",
                "gehackt",
                "worden",
                "sein",
                "."
            ]
        },
        {
            "SentenceId": 7,
            "Tokens": [
                "Dabei",
                "hatten",
                "die",
                "Hacker",
                "Zugriff",
                "auf",
                "die",
                "Website",
                "www.cmsmon.cern.ch",
                ";"
            ]
        },
        {
            "SentenceId": 8,
            "Tokens": [
                "die",
                "Hacker",
                "hinterließen",
                "dort",
                "angeblich",
                "eine",
                "griechische",
                "Botschaft",
                ",",
                "welche",
                "die",
                "Sicherheitstechniker",
                "am",
                "CERN",
                "als",
                "„",
                "einen",
                "Haufen",
                "von",
                "Schulkindern",
                "“",
                "bezeichnete",
                "."
            ]
        }
    ]
}